notebookcv/__init__.py
notebookcv/notebookcv.py
notebookcv-0.0.1.dist-info/LICENSE
notebookcv-0.0.1.dist-info/METADATA
notebookcv-0.0.1.dist-info/WHEEL
notebookcv-0.0.1.dist-info/top_level.txt
notebookcv-0.0.1.dist-info/RECORD
